lmdo/__init__.py
lmdo/chain_processor.py
lmdo/cli.py
lmdo/config.py
lmdo/config_parser.py
lmdo/file_loader.py
lmdo/file_upload_progress.py
lmdo/lmdo_config.py
lmdo/lmdo_yaml.py
lmdo/oprint.py
lmdo/spinner.py
lmdo/utc.py
lmdo/utils.py
lmdo/cmds/__init__.py
lmdo/cmds/aws_base.py
lmdo/cmds/client_factory.py
lmdo/cmds/commands.py
lmdo/cmds/api/__init__.py
lmdo/cmds/api/api_client.py
lmdo/cmds/api/apigateway.py
lmdo/cmds/bp/__init__.py
lmdo/cmds/bp/boiler_plate.py
lmdo/cmds/bp/bp_client.py
lmdo/cmds/cf/__init__.py
lmdo/cmds/cf/cf_client.py
lmdo/cmds/cf/cf_status.py
lmdo/cmds/cf/cloudformation.py
lmdo/cmds/cwe/__init__.py
lmdo/cmds/cwe/cloudwatch_event.py
lmdo/cmds/cwe/cwe_client.py
lmdo/cmds/deploy/__init__.py
lmdo/cmds/deploy/deploy_client.py
lmdo/cmds/destroy/__init__.py
lmdo/cmds/destroy/destroy_client.py
lmdo/cmds/iam/__init__.py
lmdo/cmds/iam/iam.py
lmdo/cmds/lm/__init__.py
lmdo/cmds/lm/aws_lambda.py
lmdo/cmds/lm/lm_client.py
lmdo/cmds/logs/__init__.py
lmdo/cmds/logs/logs.py
lmdo/cmds/logs/logs_client.py
lmdo/cmds/s3/__init__.py
lmdo/cmds/s3/bucket_notification.py
lmdo/cmds/s3/s3.py
lmdo/cmds/s3/s3_client.py
lmdo/cmds/sns/__init__.py
lmdo/cmds/sns/sns.py
lmdo/convertors/__init__.py
lmdo/convertors/apigateway_local_lambda_convertor.py
lmdo/convertors/apigateway_local_lambda_role_convertor.py
lmdo/convertors/convertor.py
lmdo/convertors/env_var_convertor.py
lmdo/convertors/nested_template_url_convertor.py
lmdo/convertors/params_convertor.py
lmdo/convertors/stack_var_convertor.py
lmdo/lmdo_handlers/__init__.py
lmdo/lmdo_handlers/cron_dispatcher/__init__.py
lmdo/lmdo_handlers/cron_dispatcher/events_dispatcher_handler.py
lmdo/lmdo_handlers/go/__init__.py
lmdo/lmdo_handlers/go/go_handler.py
lmdo/lmdo_handlers/heater/__init__.py
lmdo/lmdo_handlers/heater/heater_handler.py
lmdo/lmdo_handlers/wsgi/__init__.py
lmdo/lmdo_handlers/wsgi/lmdo_wsgi_handler.py
lmdo/lmdo_handlers/wsgi/wsgi_apps/__init__.py
lmdo-2.3.1.dist-info/METADATA
lmdo-2.3.1.dist-info/RECORD
lmdo-2.3.1.dist-info/WHEEL
lmdo-2.3.1.dist-info/entry_points.txt
lmdo-2.3.1.dist-info/top_level.txt
