Metadata-Version: 2.1
Name: lmdo
Version: 2.3.1
Summary: CLI tools for microservices automation using AWS Lambda function
Home-page: https://github.com/liangrog/lmdo
Author: Roger Liang
Author-email: pinguroger@gmail.com
License: MIT
Keywords: cli
Platform: UNKNOWN
Classifier: Intended Audience :: Developers
Classifier: Topic :: Utilities
Classifier: License :: OSI Approved :: Apache Software License
Classifier: Natural Language :: English
Classifier: Operating System :: OS Independent
Classifier: Programming Language :: Python :: 2
Classifier: Programming Language :: Python :: 2.6
Classifier: Programming Language :: Python :: 2.7
Provides-Extra: test
Requires-Dist: docopt (==0.6.2)
Requires-Dist: boto3 (>=1.4.2)
Requires-Dist: PyYAML (==3.12)
Requires-Dist: jinja2 (==2.8)
Requires-Dist: gitpython
Requires-Dist: lambda-packages (==0.13.0)
Provides-Extra: test
Requires-Dist: coverage; extra == 'test'
Requires-Dist: pytest; extra == 'test'
Requires-Dist: pytest-cov; extra == 'test'
